pyproject_init/__init__.py
pyproject_init/cli.py
pyproject_init/pyproject_initializer.py
pyproject_init/utils/__init__.py
pyproject_init/utils/projectfiles.py
pyproject_init/utils/pythonfiles.py
pyproject_init-1.1.0.dist-info/METADATA
pyproject_init-1.1.0.dist-info/WHEEL
pyproject_init-1.1.0.dist-info/entry_points.txt
pyproject_init-1.1.0.dist-info/licenses/LICENSE
pyproject_init-1.1.0.dist-info/RECORD
