Metadata-Version: 2.3
Name: pyproject_init
Version: 1.1.0
Summary: A tool to initialize a python project with all basic files and configurations
Project-URL: Repository, https://github.com/quentinhaenn/pyproject_init
Author-email: Quentin Haenn <quentin.haenn.pro@gmail.com>
Maintainer-email: Quentin Haenn <quentin.haenn.pro@gmail.com>
License: MIT License
License-File: LICENSE
Keywords: project,project init,python project,python project init
Classifier: Development Status :: 3 - Alpha
Classifier: Intended Audience :: Developers
Classifier: License :: OSI Approved :: MIT License
Classifier: Programming Language :: Python :: 3
Classifier: Programming Language :: Python :: 3.9
Classifier: Programming Language :: Python :: 3.10
Classifier: Programming Language :: Python :: 3.11
Classifier: Programming Language :: Python :: 3.12
Requires-Python: >=3.9
Requires-Dist: click
Requires-Dist: requests
